test_46165/init.py
test_46165/saylani.py
test_46165-0.1.dist-info/METADATA
test_46165-0.1.dist-info/WHEEL
test_46165-0.1.dist-info/top_level.txt
test_46165-0.1.dist-info/RECORD
