Metadata-Version: 2.1
Name: test-46165
Version: 0.1
Summary: This is the test Package
Author: Shahzad Ahmed Khan
License: UNKNOWN
Platform: UNKNOWN
